{
	"backtrace" : 0,
	"backtraceGraph" : 
	{
		"commands" : [],
		"files" : 
		[
			"app/glm/CMakeLists.txt"
		],
		"nodes" : 
		[
			{
				"file" : 0
			}
		]
	},
	"dependencies" : 
	[
		{
			"id" : "ZERO_CHECK::@6890427a1f51a3e7e1df"
		}
	],
	"folder" : 
	{
		"name" : "CMakePredefinedTargets"
	},
	"id" : "ALL_BUILD::@b4952d86bd891336ae9d",
	"isGeneratorProvided" : true,
	"name" : "ALL_BUILD",
	"paths" : 
	{
		"build" : "app/glm",
		"source" : "app/glm"
	},
	"sources" : [],
	"type" : "UTILITY"
}
